palabox/__init__.py
palabox/config.py
palabox/apis/__init__.py
palabox/apis/base.py
palabox/apis/codingame.py
palabox/apis/duolingo.py
palabox/apis/leetcode.py
palabox/apis/wakatime.py
palabox/apis/types/__init__.py
palabox/apis/types/codingame.py
palabox/apis/types/duolingo.py
palabox/apis/types/leetcode.py
palabox/apis/types/wakatime.py
palabox/processing/__init__.py
palabox/processing/text/__init__.py
palabox/processing/text/properly_cut_text.py
palabox/scraping/__init__.py
palabox/scraping/clean_html.py
palabox/scraping/constants.py
palabox/scraping/serverside_rendering.py
palabox/utils/__init__.py
palabox/utils/case_conversion.py
palabox/utils/dict_conversion.py
palabox/utils/json_converter.py
palabox/utils/logging.py
palabox-0.0.8.dist-info/LICENSE
palabox-0.0.8.dist-info/METADATA
palabox-0.0.8.dist-info/WHEEL
palabox-0.0.8.dist-info/top_level.txt
palabox-0.0.8.dist-info/RECORD
